configfy/__init__.py
configfy/configfile.py
configfy/decorator.py
configfy-1.0.10.dist-info/METADATA
configfy-1.0.10.dist-info/RECORD
configfy-1.0.10.dist-info/WHEEL
configfy-1.0.10.dist-info/top_level.txt
tests/__init__.py
tests/context.py
tests/simple_tests.py
