Metadata-Version: 2.1
Name: configfy
Version: 1.0.10
Summary: Decorator library to expose keyword arguments through config files
Home-page: https://github.com/mapa17/configfy
Author: Manuel Pasieka
Author-email: manuel.pasieka@protonmail.ch
License: UNKNOWN
Platform: UNKNOWN
Classifier: Programming Language :: Python :: 3
Classifier: License :: OSI Approved :: MIT License
Classifier: Operating System :: OS Independent
